distributor.sv
module distributor #(
    parameter   DATA_WIDTH = 32,
                SCREEN_WIDTH = 640,
                SCREEN_HEIGHT = 480,
                NUM_ENGINES = 2
)(
    input logic                     clk,
    input logic                     reset,
    input logic [NUM_ENGINES-1:0]   fin_bus,

    output logic [DATA_WIDTH-1:0]   xcoord          [NUM_ENGINES-1:0],
    output logic [DATA_WIDTH-1:0]   ycoord          [NUM_ENGINES-1:0],
    output logic                    reset_engines   [NUM_ENGINES-1:0]
);

logic [DATA_WIDTH-1:0]  xcount;
logic [DATA_WIDTH-1:0]  ycount;   

always_ff @(posedge clk)begin

    if(reset)begin
        for(int i = 0; i < NUM_ENGINES; i++)begin
            reset_engines[i] <= 1;
        end
        xcount <= 32'b0;
        ycount <= SCREEN_HEIGHT;
    end
    
    if(xcount == SCREEN_WIDTH)begin
        xcount <= 32'b0;
        ycount <= ycount - 1;
    end

    if(ycount == 32'b0)begin
        xcount <= 32'b0;
        ycount <= SCREEN_HEIGHT;
    end

    for(int i = 0; i < NUM_ENGINES; i++)begin
        if(fin_bus[i] == 1'b1)begin
            xcoord[i] <= xcount;
            ycoord[i] <= ycount;
            reset_engines[i] <= 1;
            xcount <= xcount + 1;
        end
    end
end

endmodule

distributor.vcd
$version Generated by VerilatedVcd $end
$date Thu Jun  6 14:44:00 2024 $end
$timescale 1ps $end

 $scope module TOP $end
  $var wire  1 ' clk $end
  $var wire  2 ) fin_bus [1:0] $end
  $var wire  1 ( reset $end
  $var wire  1 . reset_engines[0] $end
  $var wire  1 / reset_engines[1] $end
  $var wire 32 * xcoord[0] [31:0] $end
  $var wire 32 + xcoord[1] [31:0] $end
  $var wire 32 , ycoord[0] [31:0] $end
  $var wire 32 - ycoord[1] [31:0] $end
  $scope module distributor $end
   $var wire 32 0 DATA_WIDTH [31:0] $end
   $var wire 32 3 NUM_ENGINES [31:0] $end
   $var wire 32 2 SCREEN_HEIGHT [31:0] $end
   $var wire 32 1 SCREEN_WIDTH [31:0] $end
   $var wire  1 ' clk $end
   $var wire  2 ) fin_bus [1:0] $end
   $var wire  1 ( reset $end
   $var wire  1 . reset_engines[0] $end
   $var wire  1 / reset_engines[1] $end
   $var wire 32 * xcoord[0] [31:0] $end
   $var wire 32 + xcoord[1] [31:0] $end
   $var wire 32 # xcount [31:0] $end
   $var wire 32 , ycoord[0] [31:0] $end
   $var wire 32 - ycoord[1] [31:0] $end
   $var wire 32 $ ycount [31:0] $end
   $scope module unnamedblk1 $end
    $var wire 32 % i [31:0] $end
   $upscope $end
   $scope module unnamedblk2 $end
    $var wire 32 & i [31:0] $end
   $upscope $end
  $upscope $end
 $upscope $end
$enddefinitions $end


#0
b00000000000000000000000000000000 #
b00000000000000000000000000000000 $
b00000000000000000000000000000000 %
b00000000000000000000000000000000 &
1'
1(
b11 )
b00000000000000000000000000000000 *
b00000000000000000000000000000000 +
b00000000000000000000000000000000 ,
b00000000000000000000000000000000 -
0.
0/
b00000000000000000000000000100000 0
b00000000000000000000001010000000 1
b00000000000000000000000111100000 2
b00000000000000000000000000000010 3
#1
0'
#2
b00000000000000000000000000000001 #
b00000000000000000000000111100000 $
b00000000000000000000000000000010 %
b00000000000000000000000000000010 &
1'
1.
1/
#3
0'
#4
b00000000000000000000000000000010 #
1'
b00000000000000000000000000000001 *
b00000000000000000000000000000001 +
b00000000000000000000000111100000 ,
b00000000000000000000000111100000 -
#5
0'
#6
b00000000000000000000000000000011 #
1'
b00000000000000000000000000000010 *
b00000000000000000000000000000010 +
#7
0'
#8
b00000000000000000000000000000100 #
1'
b00000000000000000000000000000011 *
b00000000000000000000000000000011 +
#9
0'
#10
b00000000000000000000000000000101 #
1'
b00000000000000000000000000000100 *
b00000000000000000000000000000100 +
#11
0'
#12
b00000000000000000000000000000110 #
1'
b00000000000000000000000000000101 *
b00000000000000000000000000000101 +
#13
0'
#14
b00000000000000000000000000000111 #
1'
b00000000000000000000000000000110 *
b00000000000000000000000000000110 +
#15
0'
#16
b00000000000000000000000000001000 #
1'
b00000000000000000000000000000111 *
b00000000000000000000000000000111 +
#17
0'
#18
b00000000000000000000000000001001 #
1'
b00000000000000000000000000001000 *
b00000000000000000000000000001000 +
#19
0'
#20
b00000000000000000000000000001010 #
1'
b00000000000000000000000000001001 *
b00000000000000000000000000001001 +
#21
0'
#22
b00000000000000000000000000001011 #
1'
b00000000000000000000000000001010 *
b00000000000000000000000000001010 +
#23
0'
#24
b00000000000000000000000000001100 #
1'
b00000000000000000000000000001011 *
b00000000000000000000000000001011 +
#25
0'
#26
b00000000000000000000000000001101 #
1'
b00000000000000000000000000001100 *
b00000000000000000000000000001100 +
#27
0'
#28
b00000000000000000000000000001110 #
1'
b00000000000000000000000000001101 *
b00000000000000000000000000001101 +
#29
0'
#30
b00000000000000000000000000001111 #
1'
b00000000000000000000000000001110 *
b00000000000000000000000000001110 +
#31
0'
#32
b00000000000000000000000000010000 #
1'
b00000000000000000000000000001111 *
b00000000000000000000000000001111 +
#33
0'
#34
b00000000000000000000000000010001 #
1'
b00000000000000000000000000010000 *
b00000000000000000000000000010000 +
#35
0'
#36
b00000000000000000000000000010010 #
1'
b00000000000000000000000000010001 *
b00000000000000000000000000010001 +
#37
0'
#38
b00000000000000000000000000010011 #
1'
b00000000000000000000000000010010 *
b00000000000000000000000000010010 +
#39
0'
#40
b00000000000000000000000000010100 #
1'
b00000000000000000000000000010011 *
b00000000000000000000000000010011 +
#41
0'
#42
b00000000000000000000000000010101 #
1'
b00000000000000000000000000010100 *
b00000000000000000000000000010100 +
#43
0'
#44
b00000000000000000000000000010110 #
1'
b00000000000000000000000000010101 *
b00000000000000000000000000010101 +
#45
0'
#46
b00000000000000000000000000010111 #
1'
b00000000000000000000000000010110 *
b00000000000000000000000000010110 +
#47
0'
#48
b00000000000000000000000000011000 #
1'
b00000000000000000000000000010111 *
b00000000000000000000000000010111 +
#49
0'
#50
b00000000000000000000000000011001 #
1'
b00000000000000000000000000011000 *
b00000000000000000000000000011000 +
#51
0'
#52
b00000000000000000000000000011010 #
1'
b00000000000000000000000000011001 *
b00000000000000000000000000011001 +
#53
0'
#54
b00000000000000000000000000011011 #
1'
b00000000000000000000000000011010 *
b00000000000000000000000000011010 +
#55
0'
#56
b00000000000000000000000000011100 #
1'
b00000000000000000000000000011011 *
b00000000000000000000000000011011 +
#57
0'
#58
b00000000000000000000000000011101 #
1'
b00000000000000000000000000011100 *
b00000000000000000000000000011100 +
#59
0'
#60
b00000000000000000000000000011110 #
1'
b00000000000000000000000000011101 *
b00000000000000000000000000011101 +
#61
0'
#62
b00000000000000000000000000011111 #
1'
b00000000000000000000000000011110 *
b00000000000000000000000000011110 +
#63
0'
#64
b00000000000000000000000000100000 #
1'
b00000000000000000000000000011111 *
b00000000000000000000000000011111 +
#65
0'
#66
b00000000000000000000000000100001 #
1'
b00000000000000000000000000100000 *
b00000000000000000000000000100000 +
#67
0'
#68
b00000000000000000000000000100010 #
1'
b00000000000000000000000000100001 *
b00000000000000000000000000100001 +
#69
0'
#70
b00000000000000000000000000100011 #
1'
b00000000000000000000000000100010 *
b00000000000000000000000000100010 +
#71
0'
#72
b00000000000000000000000000100100 #
1'
b00000000000000000000000000100011 *
b00000000000000000000000000100011 +
#73
0'
#74
b00000000000000000000000000100101 #
1'
b00000000000000000000000000100100 *
b00000000000000000000000000100100 +
#75
0'
#76
b00000000000000000000000000100110 #
1'
b00000000000000000000000000100101 *
b00000000000000000000000000100101 +
#77
0'
#78
b00000000000000000000000000100111 #
1'
b00000000000000000000000000100110 *
b00000000000000000000000000100110 +
#79
0'
#80
b00000000000000000000000000101000 #
1'
b00000000000000000000000000100111 *
b00000000000000000000000000100111 +
#81
0'
#82
b00000000000000000000000000101001 #
1'
b00000000000000000000000000101000 *
b00000000000000000000000000101000 +
#83
0'
#84
b00000000000000000000000000101010 #
1'
b00000000000000000000000000101001 *
b00000000000000000000000000101001 +
#85
0'
#86
b00000000000000000000000000101011 #
1'
b00000000000000000000000000101010 *
b00000000000000000000000000101010 +
#87
0'
#88
b00000000000000000000000000101100 #
1'
b00000000000000000000000000101011 *
b00000000000000000000000000101011 +
#89
0'
#90
b00000000000000000000000000101101 #
1'
b00000000000000000000000000101100 *
b00000000000000000000000000101100 +
#91
0'
#92
b00000000000000000000000000101110 #
1'
b00000000000000000000000000101101 *
b00000000000000000000000000101101 +
#93
0'
#94
b00000000000000000000000000101111 #
1'
b00000000000000000000000000101110 *
b00000000000000000000000000101110 +
#95
0'
#96
b00000000000000000000000000110000 #
1'
b00000000000000000000000000101111 *
b00000000000000000000000000101111 +
#97
0'
#98
b00000000000000000000000000110001 #
1'
b00000000000000000000000000110000 *
b00000000000000000000000000110000 +
#99
0'
#100
b00000000000000000000000000110010 #
1'
b00000000000000000000000000110001 *
b00000000000000000000000000110001 +
#101
0'
#102
b00000000000000000000000000110011 #
1'
b00000000000000000000000000110010 *
b00000000000000000000000000110010 +
#103
0'
#104
b00000000000000000000000000110100 #
1'
b00000000000000000000000000110011 *
b00000000000000000000000000110011 +
#105
0'
#106
b00000000000000000000000000110101 #
1'
b00000000000000000000000000110100 *
b00000000000000000000000000110100 +
#107
0'
#108
b00000000000000000000000000110110 #
1'
b00000000000000000000000000110101 *
b00000000000000000000000000110101 +
#109
0'
#110
b00000000000000000000000000110111 #
1'
b00000000000000000000000000110110 *
b00000000000000000000000000110110 +
#111
0'
#112
b00000000000000000000000000111000 #
1'
b00000000000000000000000000110111 *
b00000000000000000000000000110111 +
#113
0'
#114
b00000000000000000000000000111001 #
1'
b00000000000000000000000000111000 *
b00000000000000000000000000111000 +
#115
0'
#116
b00000000000000000000000000111010 #
1'
b00000000000000000000000000111001 *
b00000000000000000000000000111001 +
#117
0'
#118
b00000000000000000000000000111011 #
1'
b00000000000000000000000000111010 *
b00000000000000000000000000111010 +
#119
0'
#120
b00000000000000000000000000111100 #
1'
b00000000000000000000000000111011 *
b00000000000000000000000000111011 +
#121
0'
#122
b00000000000000000000000000111101 #
1'
b00000000000000000000000000111100 *
b00000000000000000000000000111100 +
#123
0'
#124
b00000000000000000000000000111110 #
1'
b00000000000000000000000000111101 *
b00000000000000000000000000111101 +
#125
0'
#126
b00000000000000000000000000111111 #
1'
b00000000000000000000000000111110 *
b00000000000000000000000000111110 +
#127
0'
#128
b00000000000000000000000001000000 #
1'
b00000000000000000000000000111111 *
b00000000000000000000000000111111 +
#129
0'
#130
b00000000000000000000000001000001 #
1'
b00000000000000000000000001000000 *
b00000000000000000000000001000000 +
#131
0'
#132
b00000000000000000000000001000010 #
1'
b00000000000000000000000001000001 *
b00000000000000000000000001000001 +
#133
0'
#134
b00000000000000000000000001000011 #
1'
b00000000000000000000000001000010 *
b00000000000000000000000001000010 +
#135
0'
#136
b00000000000000000000000001000100 #
1'
b00000000000000000000000001000011 *
b00000000000000000000000001000011 +
#137
0'
#138
b00000000000000000000000001000101 #
1'
b00000000000000000000000001000100 *
b00000000000000000000000001000100 +
#139
0'
#140
b00000000000000000000000001000110 #
1'
b00000000000000000000000001000101 *
b00000000000000000000000001000101 +
#141
0'
#142
b00000000000000000000000001000111 #
1'
b00000000000000000000000001000110 *
b00000000000000000000000001000110 +
#143
0'
#144
b00000000000000000000000001001000 #
1'
b00000000000000000000000001000111 *
b00000000000000000000000001000111 +
#145
0'
#146
b00000000000000000000000001001001 #
1'
b00000000000000000000000001001000 *
b00000000000000000000000001001000 +
#147
0'
#148
b00000000000000000000000001001010 #
1'
b00000000000000000000000001001001 *
b00000000000000000000000001001001 +
#149
0'
#150
b00000000000000000000000001001011 #
1'
b00000000000000000000000001001010 *
b00000000000000000000000001001010 +
#151
0'
#152
b00000000000000000000000001001100 #
1'
b00000000000000000000000001001011 *
b00000000000000000000000001001011 +
#153
0'
#154
b00000000000000000000000001001101 #
1'
b00000000000000000000000001001100 *
b00000000000000000000000001001100 +
#155
0'
#156
b00000000000000000000000001001110 #
1'
b00000000000000000000000001001101 *
b00000000000000000000000001001101 +
#157
0'
#158
b00000000000000000000000001001111 #
1'
b00000000000000000000000001001110 *
b00000000000000000000000001001110 +
#159
0'
#160
b00000000000000000000000001010000 #
1'
b00000000000000000000000001001111 *
b00000000000000000000000001001111 +
#161
0'
#162
b00000000000000000000000001010001 #
1'
b00000000000000000000000001010000 *
b00000000000000000000000001010000 +
#163
0'
#164
b00000000000000000000000001010010 #
1'
b00000000000000000000000001010001 *
b00000000000000000000000001010001 +
#165
0'
#166
b00000000000000000000000001010011 #
1'
b00000000000000000000000001010010 *
b00000000000000000000000001010010 +
#167
0'
#168
b00000000000000000000000001010100 #
1'
b00000000000000000000000001010011 *
b00000000000000000000000001010011 +
#169
0'
#170
b00000000000000000000000001010101 #
1'
b00000000000000000000000001010100 *
b00000000000000000000000001010100 +
#171
0'
#172
b00000000000000000000000001010110 #
1'
b00000000000000000000000001010101 *
b00000000000000000000000001010101 +
#173
0'
#174
b00000000000000000000000001010111 #
1'
b00000000000000000000000001010110 *
b00000000000000000000000001010110 +
#175
0'
#176
b00000000000000000000000001011000 #
1'
b00000000000000000000000001010111 *
b00000000000000000000000001010111 +
#177
0'
#178
b00000000000000000000000001011001 #
1'
b00000000000000000000000001011000 *
b00000000000000000000000001011000 +
#179
0'
#180
b00000000000000000000000001011010 #
1'
b00000000000000000000000001011001 *
b00000000000000000000000001011001 +
#181
0'
#182
b00000000000000000000000001011011 #
1'
b00000000000000000000000001011010 *
b00000000000000000000000001011010 +
#183
0'
#184
b00000000000000000000000001011100 #
1'
b00000000000000000000000001011011 *
b00000000000000000000000001011011 +
#185
0'
#186
b00000000000000000000000001011101 #
1'
b00000000000000000000000001011100 *
b00000000000000000000000001011100 +
#187
0'
#188
b00000000000000000000000001011110 #
1'
b00000000000000000000000001011101 *
b00000000000000000000000001011101 +
#189
0'
#190
b00000000000000000000000001011111 #
1'
b00000000000000000000000001011110 *
b00000000000000000000000001011110 +
#191
0'
#192
b00000000000000000000000001100000 #
1'
b00000000000000000000000001011111 *
b00000000000000000000000001011111 +
#193
0'
#194
b00000000000000000000000001100001 #
1'
b00000000000000000000000001100000 *
b00000000000000000000000001100000 +
#195
0'
#196
b00000000000000000000000001100010 #
1'
b00000000000000000000000001100001 *
b00000000000000000000000001100001 +
#197
0'
#198
b00000000000000000000000001100011 #
1'
b00000000000000000000000001100010 *
b00000000000000000000000001100010 +
#199
0'
#200
b00000000000000000000000001100100 #
1'
b00000000000000000000000001100011 *
b00000000000000000000000001100011 +
#201
0'
#202
b00000000000000000000000001100101 #
1'
b00000000000000000000000001100100 *
b00000000000000000000000001100100 +
#203
0'
#204
b00000000000000000000000001100110 #
1'
b00000000000000000000000001100101 *
b00000000000000000000000001100101 +
#205
0'
#206
b00000000000000000000000001100111 #
1'
b00000000000000000000000001100110 *
b00000000000000000000000001100110 +
#207
0'
#208
b00000000000000000000000001101000 #
1'
b00000000000000000000000001100111 *
b00000000000000000000000001100111 +
#209
0'
#210
b00000000000000000000000001101001 #
1'
b00000000000000000000000001101000 *
b00000000000000000000000001101000 +
#211
0'
#212
b00000000000000000000000001101010 #
1'
b00000000000000000000000001101001 *
b00000000000000000000000001101001 +
#213
0'
#214
b00000000000000000000000001101011 #
1'
b00000000000000000000000001101010 *
b00000000000000000000000001101010 +
#215
0'
#216
b00000000000000000000000001101100 #
1'
b00000000000000000000000001101011 *
b00000000000000000000000001101011 +
#217
0'
#218
b00000000000000000000000001101101 #
1'
b00000000000000000000000001101100 *
b00000000000000000000000001101100 +
#219
0'
#220
b00000000000000000000000001101110 #
1'
b00000000000000000000000001101101 *
b00000000000000000000000001101101 +
#221
0'
#222
b00000000000000000000000001101111 #
1'
b00000000000000000000000001101110 *
b00000000000000000000000001101110 +
#223
0'
#224
b00000000000000000000000001110000 #
1'
b00000000000000000000000001101111 *
b00000000000000000000000001101111 +
#225
0'
#226
b00000000000000000000000001110001 #
1'
b00000000000000000000000001110000 *
b00000000000000000000000001110000 +
#227
0'
#228
b00000000000000000000000001110010 #
1'
b00000000000000000000000001110001 *
b00000000000000000000000001110001 +
#229
0'
#230
b00000000000000000000000001110011 #
1'
b00000000000000000000000001110010 *
b00000000000000000000000001110010 +
#231
0'
#232
b00000000000000000000000001110100 #
1'
b00000000000000000000000001110011 *
b00000000000000000000000001110011 +
#233
0'
#234
b00000000000000000000000001110101 #
1'
b00000000000000000000000001110100 *
b00000000000000000000000001110100 +
#235
0'
#236
b00000000000000000000000001110110 #
1'
b00000000000000000000000001110101 *
b00000000000000000000000001110101 +
#237
0'
#238
b00000000000000000000000001110111 #
1'
b00000000000000000000000001110110 *
b00000000000000000000000001110110 +
#239
0'
#240
b00000000000000000000000001111000 #
1'
b00000000000000000000000001110111 *
b00000000000000000000000001110111 +
#241
0'
#242
b00000000000000000000000001111001 #
1'
b00000000000000000000000001111000 *
b00000000000000000000000001111000 +
#243
0'
#244
b00000000000000000000000001111010 #
1'
b00000000000000000000000001111001 *
b00000000000000000000000001111001 +
#245
0'
#246
b00000000000000000000000001111011 #
1'
b00000000000000000000000001111010 *
b00000000000000000000000001111010 +
#247
0'
#248
b00000000000000000000000001111100 #
1'
b00000000000000000000000001111011 *
b00000000000000000000000001111011 +
#249
0'
#250
b00000000000000000000000001111101 #
1'
b00000000000000000000000001111100 *
b00000000000000000000000001111100 +
#251
0'
#252
b00000000000000000000000001111110 #
1'
b00000000000000000000000001111101 *
b00000000000000000000000001111101 +
#253
0'
#254
b00000000000000000000000001111111 #
1'
b00000000000000000000000001111110 *
b00000000000000000000000001111110 +
#255
0'
#256
b00000000000000000000000010000000 #
1'
b00000000000000000000000001111111 *
b00000000000000000000000001111111 +
#257
0'
#258
b00000000000000000000000010000001 #
1'
b00000000000000000000000010000000 *
b00000000000000000000000010000000 +
#259
0'
#260
b00000000000000000000000010000010 #
1'
b00000000000000000000000010000001 *
b00000000000000000000000010000001 +
#261
0'
#262
b00000000000000000000000010000011 #
1'
b00000000000000000000000010000010 *
b00000000000000000000000010000010 +
#263
0'
#264
b00000000000000000000000010000100 #
1'
b00000000000000000000000010000011 *
b00000000000000000000000010000011 +
#265
0'
#266
b00000000000000000000000010000101 #
1'
b00000000000000000000000010000100 *
b00000000000000000000000010000100 +
#267
0'
#268
b00000000000000000000000010000110 #
1'
b00000000000000000000000010000101 *
b00000000000000000000000010000101 +
#269
0'
#270
b00000000000000000000000010000111 #
1'
b00000000000000000000000010000110 *
b00000000000000000000000010000110 +
#271
0'
#272
b00000000000000000000000010001000 #
1'
b00000000000000000000000010000111 *
b00000000000000000000000010000111 +
#273
0'
#274
b00000000000000000000000010001001 #
1'
b00000000000000000000000010001000 *
b00000000000000000000000010001000 +
#275
0'
#276
b00000000000000000000000010001010 #
1'
b00000000000000000000000010001001 *
b00000000000000000000000010001001 +
#277
0'
#278
b00000000000000000000000010001011 #
1'
b00000000000000000000000010001010 *
b00000000000000000000000010001010 +
#279
0'
#280
b00000000000000000000000010001100 #
1'
b00000000000000000000000010001011 *
b00000000000000000000000010001011 +
#281
0'
#282
b00000000000000000000000010001101 #
1'
b00000000000000000000000010001100 *
b00000000000000000000000010001100 +
#283
0'
#284
b00000000000000000000000010001110 #
1'
b00000000000000000000000010001101 *
b00000000000000000000000010001101 +
#285
0'
#286
b00000000000000000000000010001111 #
1'
b00000000000000000000000010001110 *
b00000000000000000000000010001110 +
#287
0'
#288
b00000000000000000000000010010000 #
1'
b00000000000000000000000010001111 *
b00000000000000000000000010001111 +
#289
0'
#290
b00000000000000000000000010010001 #
1'
b00000000000000000000000010010000 *
b00000000000000000000000010010000 +
#291
0'
#292
b00000000000000000000000010010010 #
1'
b00000000000000000000000010010001 *
b00000000000000000000000010010001 +
#293
0'
#294
b00000000000000000000000010010011 #
1'
b00000000000000000000000010010010 *
b00000000000000000000000010010010 +
#295
0'
#296
b00000000000000000000000010010100 #
1'
b00000000000000000000000010010011 *
b00000000000000000000000010010011 +
#297
0'
#298
b00000000000000000000000010010101 #
1'
b00000000000000000000000010010100 *
b00000000000000000000000010010100 +
#299
0'
#300
b00000000000000000000000010010110 #
1'
b00000000000000000000000010010101 *
b00000000000000000000000010010101 +
#301
0'
#302
b00000000000000000000000010010111 #
1'
b00000000000000000000000010010110 *
b00000000000000000000000010010110 +
#303
0'
#304
b00000000000000000000000010011000 #
1'
b00000000000000000000000010010111 *
b00000000000000000000000010010111 +
#305
0'
#306
b00000000000000000000000010011001 #
1'
b00000000000000000000000010011000 *
b00000000000000000000000010011000 +
#307
0'
#308
b00000000000000000000000010011010 #
1'
b00000000000000000000000010011001 *
b00000000000000000000000010011001 +
#309
0'
#310
b00000000000000000000000010011011 #
1'
b00000000000000000000000010011010 *
b00000000000000000000000010011010 +
#311
0'
#312
b00000000000000000000000010011100 #
1'
b00000000000000000000000010011011 *
b00000000000000000000000010011011 +
#313
0'
#314
b00000000000000000000000010011101 #
1'
b00000000000000000000000010011100 *
b00000000000000000000000010011100 +
#315
0'
#316
b00000000000000000000000010011110 #
1'
b00000000000000000000000010011101 *
b00000000000000000000000010011101 +
#317
0'
#318
b00000000000000000000000010011111 #
1'
b00000000000000000000000010011110 *
b00000000000000000000000010011110 +
#319
0'
#320
b00000000000000000000000010100000 #
1'
b00000000000000000000000010011111 *
b00000000000000000000000010011111 +
#321
0'
#322
b00000000000000000000000010100001 #
1'
b00000000000000000000000010100000 *
b00000000000000000000000010100000 +
#323
0'
#324
b00000000000000000000000010100010 #
1'
b00000000000000000000000010100001 *
b00000000000000000000000010100001 +
#325
0'
#326
b00000000000000000000000010100011 #
1'
b00000000000000000000000010100010 *
b00000000000000000000000010100010 +
#327
0'
#328
b00000000000000000000000010100100 #
1'
b00000000000000000000000010100011 *
b00000000000000000000000010100011 +
#329
0'
#330
b00000000000000000000000010100101 #
1'
b00000000000000000000000010100100 *
b00000000000000000000000010100100 +
#331
0'
#332
b00000000000000000000000010100110 #
1'
b00000000000000000000000010100101 *
b00000000000000000000000010100101 +
#333
0'
#334
b00000000000000000000000010100111 #
1'
b00000000000000000000000010100110 *
b00000000000000000000000010100110 +
#335
0'
#336
b00000000000000000000000010101000 #
1'
b00000000000000000000000010100111 *
b00000000000000000000000010100111 +
#337
0'
#338
b00000000000000000000000010101001 #
1'
b00000000000000000000000010101000 *
b00000000000000000000000010101000 +
#339
0'
#340
b00000000000000000000000010101010 #
1'
b00000000000000000000000010101001 *
b00000000000000000000000010101001 +
#341
0'
#342
b00000000000000000000000010101011 #
1'
b00000000000000000000000010101010 *
b00000000000000000000000010101010 +
#343
0'
#344
b00000000000000000000000010101100 #
1'
b00000000000000000000000010101011 *
b00000000000000000000000010101011 +
#345
0'
#346
b00000000000000000000000010101101 #
1'
b00000000000000000000000010101100 *
b00000000000000000000000010101100 +
#347
0'
#348
b00000000000000000000000010101110 #
1'
b00000000000000000000000010101101 *
b00000000000000000000000010101101 +
#349
0'
#350
b00000000000000000000000010101111 #
1'
b00000000000000000000000010101110 *
b00000000000000000000000010101110 +
#351
0'
#352
b00000000000000000000000010110000 #
1'
b00000000000000000000000010101111 *
b00000000000000000000000010101111 +
#353
0'
#354
b00000000000000000000000010110001 #
1'
b00000000000000000000000010110000 *
b00000000000000000000000010110000 +
#355
0'
#356
b00000000000000000000000010110010 #
1'
b00000000000000000000000010110001 *
b00000000000000000000000010110001 +
#357
0'
#358
b00000000000000000000000010110011 #
1'
b00000000000000000000000010110010 *
b00000000000000000000000010110010 +
#359
0'
#360
b00000000000000000000000010110100 #
1'
b00000000000000000000000010110011 *
b00000000000000000000000010110011 +
#361
0'
#362
b00000000000000000000000010110101 #
1'
b00000000000000000000000010110100 *
b00000000000000000000000010110100 +
#363
0'
#364
b00000000000000000000000010110110 #
1'
b00000000000000000000000010110101 *
b00000000000000000000000010110101 +
#365
0'
#366
b00000000000000000000000010110111 #
1'
b00000000000000000000000010110110 *
b00000000000000000000000010110110 +
#367
0'
#368
b00000000000000000000000010111000 #
1'
b00000000000000000000000010110111 *
b00000000000000000000000010110111 +
#369
0'
#370
b00000000000000000000000010111001 #
1'
b00000000000000000000000010111000 *
b00000000000000000000000010111000 +
#371
0'
#372
b00000000000000000000000010111010 #
1'
b00000000000000000000000010111001 *
b00000000000000000000000010111001 +
#373
0'
#374
b00000000000000000000000010111011 #
1'
b00000000000000000000000010111010 *
b00000000000000000000000010111010 +
#375
0'
#376
b00000000000000000000000010111100 #
1'
b00000000000000000000000010111011 *
b00000000000000000000000010111011 +
#377
0'
#378
b00000000000000000000000010111101 #
1'
b00000000000000000000000010111100 *
b00000000000000000000000010111100 +
#379
0'
#380
b00000000000000000000000010111110 #
1'
b00000000000000000000000010111101 *
b00000000000000000000000010111101 +
#381
0'
#382
b00000000000000000000000010111111 #
1'
b00000000000000000000000010111110 *
b00000000000000000000000010111110 +
#383
0'
#384
b00000000000000000000000011000000 #
1'
b00000000000000000000000010111111 *
b00000000000000000000000010111111 +
#385
0'
#386
b00000000000000000000000011000001 #
1'
b00000000000000000000000011000000 *
b00000000000000000000000011000000 +
#387
0'
#388
b00000000000000000000000011000010 #
1'
b00000000000000000000000011000001 *
b00000000000000000000000011000001 +
#389
0'
#390
b00000000000000000000000011000011 #
1'
b00000000000000000000000011000010 *
b00000000000000000000000011000010 +
#391
0'
#392
b00000000000000000000000011000100 #
1'
b00000000000000000000000011000011 *
b00000000000000000000000011000011 +
#393
0'
#394
b00000000000000000000000011000101 #
1'
b00000000000000000000000011000100 *
b00000000000000000000000011000100 +
#395
0'
#396
b00000000000000000000000011000110 #
1'
b00000000000000000000000011000101 *
b00000000000000000000000011000101 +
#397
0'
#398
b00000000000000000000000011000111 #
1'
b00000000000000000000000011000110 *
b00000000000000000000000011000110 +
#399
0'
#400
b00000000000000000000000011001000 #
1'
b00000000000000000000000011000111 *
b00000000000000000000000011000111 +
#401
0'
#402
b00000000000000000000000011001001 #
1'
b00000000000000000000000011001000 *
b00000000000000000000000011001000 +
#403
0'
#404
b00000000000000000000000011001010 #
1'
b00000000000000000000000011001001 *
b00000000000000000000000011001001 +
#405
0'
#406
b00000000000000000000000011001011 #
1'
b00000000000000000000000011001010 *
b00000000000000000000000011001010 +
#407
0'
#408
b00000000000000000000000011001100 #
1'
b00000000000000000000000011001011 *
b00000000000000000000000011001011 +
#409
0'
#410
b00000000000000000000000011001101 #
1'
b00000000000000000000000011001100 *
b00000000000000000000000011001100 +
#411
0'
#412
b00000000000000000000000011001110 #
1'
b00000000000000000000000011001101 *
b00000000000000000000000011001101 +
#413
0'
#414
b00000000000000000000000011001111 #
1'
b00000000000000000000000011001110 *
b00000000000000000000000011001110 +
#415
0'
#416
b00000000000000000000000011010000 #
1'
b00000000000000000000000011001111 *
b00000000000000000000000011001111 +
#417
0'
#418
b00000000000000000000000011010001 #
1'
b00000000000000000000000011010000 *
b00000000000000000000000011010000 +
#419
0'
#420
b00000000000000000000000011010010 #
1'
b00000000000000000000000011010001 *
b00000000000000000000000011010001 +
#421
0'
#422
b00000000000000000000000011010011 #
1'
b00000000000000000000000011010010 *
b00000000000000000000000011010010 +
#423
0'
#424
b00000000000000000000000011010100 #
1'
b00000000000000000000000011010011 *
b00000000000000000000000011010011 +
#425
0'
#426
b00000000000000000000000011010101 #
1'
b00000000000000000000000011010100 *
b00000000000000000000000011010100 +
#427
0'
#428
b00000000000000000000000011010110 #
1'
b00000000000000000000000011010101 *
b00000000000000000000000011010101 +
#429
0'
#430
b00000000000000000000000011010111 #
1'
b00000000000000000000000011010110 *
b00000000000000000000000011010110 +
#431
0'
#432
b00000000000000000000000011011000 #
1'
b00000000000000000000000011010111 *
b00000000000000000000000011010111 +
#433
0'
#434
b00000000000000000000000011011001 #
1'
b00000000000000000000000011011000 *
b00000000000000000000000011011000 +
#435
0'
#436
b00000000000000000000000011011010 #
1'
b00000000000000000000000011011001 *
b00000000000000000000000011011001 +
#437
0'
#438
b00000000000000000000000011011011 #
1'
b00000000000000000000000011011010 *
b00000000000000000000000011011010 +
#439
0'
#440
b00000000000000000000000011011100 #
1'
b00000000000000000000000011011011 *
b00000000000000000000000011011011 +
#441
0'
#442
b00000000000000000000000011011101 #
1'
b00000000000000000000000011011100 *
b00000000000000000000000011011100 +
#443
0'
#444
b00000000000000000000000011011110 #
1'
b00000000000000000000000011011101 *
b00000000000000000000000011011101 +
#445
0'
#446
b00000000000000000000000011011111 #
1'
b00000000000000000000000011011110 *
b00000000000000000000000011011110 +
#447
0'
#448
b00000000000000000000000011100000 #
1'
b00000000000000000000000011011111 *
b00000000000000000000000011011111 +
#449
0'
#450
b00000000000000000000000011100001 #
1'
b00000000000000000000000011100000 *
b00000000000000000000000011100000 +
#451
0'
#452
b00000000000000000000000011100010 #
1'
b00000000000000000000000011100001 *
b00000000000000000000000011100001 +
#453
0'
#454
b00000000000000000000000011100011 #
1'
b00000000000000000000000011100010 *
b00000000000000000000000011100010 +
#455
0'
#456
b00000000000000000000000011100100 #
1'
b00000000000000000000000011100011 *
b00000000000000000000000011100011 +
#457
0'
#458
b00000000000000000000000011100101 #
1'
b00000000000000000000000011100100 *
b00000000000000000000000011100100 +
#459
0'
#460
b00000000000000000000000011100110 #
1'
b00000000000000000000000011100101 *
b00000000000000000000000011100101 +
#461
0'
#462
b00000000000000000000000011100111 #
1'
b00000000000000000000000011100110 *
b00000000000000000000000011100110 +
#463
0'
#464
b00000000000000000000000011101000 #
1'
b00000000000000000000000011100111 *
b00000000000000000000000011100111 +
#465
0'
#466
b00000000000000000000000011101001 #
1'
b00000000000000000000000011101000 *
b00000000000000000000000011101000 +
#467
0'
#468
b00000000000000000000000011101010 #
1'
b00000000000000000000000011101001 *
b00000000000000000000000011101001 +
#469
0'
#470
b00000000000000000000000011101011 #
1'
b00000000000000000000000011101010 *
b00000000000000000000000011101010 +
#471
0'
