combinator.sv
module combinator #(
    parameter   DATA_WIDTH = 32,
                RBG_SIZE = 24,
                SCREEN_WIDTH = 640,
                SCREEN_HEIGHT = 480
)(
    input logic                     clk,
    input logic                     reset,
    input logic [RBG_SIZE-1:0]      colour_i,
    input logic                     en,
    input logic                     ready,

    output logic [DATA_WIDTH-1:0]   next_xpixel,
    output logic [DATA_WIDTH-1:0]   next_ypixel,
    output logic [RBG_SIZE-1:0]     colour_o,
    
    // flags for pixel generator
    output logic                    first,
    output logic                    last_x,
    output logic                    last_y,
    output logic                    valid

);

logic [DATA_WIDTH-1:0] xcount;
logic [DATA_WIDTH-1:0] ycount;

always_ff @(posedge clk) begin
    if(reset)begin
        xcount <= 0;
        ycount <= SCREEN_HEIGHT;
    end

    last_x <= (xcount == SCREEN_WIDTH) ? 1 : 0;
    last_y <= (ycount == 1) ? 1 : 0;
    first <= ((xcount == 0) & (ycount == SCREEN_HEIGHT)) ? 1: 0;

    if(xcount == SCREEN_WIDTH)begin
        last_x <= 1;
        xcount <= 0;
        ycount <= ycount - 1;
    end

    if(ycount == 0)begin // this might be wrong
        ycount <= SCREEN_HEIGHT;
        xcount <= 0;
    end

    if((en)&&(ready))begin
        colour_o <= colour_i;
        valid <= 1;
        xcount <= xcount + 1;
    end
    next_xpixel <= xcount;
    next_ypixel <= ycount;
end

endmodule

queue.sv
module queue #(
    parameter   DATA_WIDTH = 32,
                QUEUE_SIZE = 5,
                COUNTER_SIZE = 3,
                RBG_SIZE = 24
)(
    input logic                     clk,
    input logic                     reset,
    input logic                     fin_flag,
    // received from the engine
    input logic [RBG_SIZE-1:0]      colour_i,
    input logic [DATA_WIDTH-1:0]    xpixel_i,
    input logic [DATA_WIDTH-1:0]    ypixel_i,
    
    //received from the comibinator to check if front of queue is the next coord
    input logic [DATA_WIDTH-1:0]    xpixel_check,
    input logic [DATA_WIDTH-1:0]    ypixel_check,

    output logic [RBG_SIZE-1:0]     colour_o,
    output logic                    full_queue,      // this flag will go to the distributor
    output logic                    en
);

logic [RBG_SIZE-1:0] colour_queue [QUEUE_SIZE-1:0];
logic [DATA_WIDTH-1:0] xqueue [QUEUE_SIZE-1:0];
logic [DATA_WIDTH-1:0] yqueue [QUEUE_SIZE-1:0];
logic [COUNTER_SIZE-1:0] counter;

always_comb begin
    if((xpixel_check == xqueue[0])&&(ypixel_check == yqueue[0]))begin
        en = 1;
    end
end

always_ff @(posedge clk) begin
    if(reset)begin
        counter <= 0;
        for(int i = 0; i < QUEUE_SIZE; i++)begin
            colour_queue[i] <= 0;
        end
    end
    else begin
        if(counter == QUEUE_SIZE - 1)begin
            full_queue <= 1;
        end
        else begin
            full_queue <= 0;
        end

        if((xpixel_check == xqueue[0])&&(ypixel_check == yqueue[0]))begin
            colour_o <= colour_queue[0];
            for(int i = 0; i < QUEUE_SIZE-1; i++)begin                    
                colour_queue[i] <= colour_queue[i + 1];
                xqueue[i] <= xqueue[i+1];
                yqueue[i] <= yqueue[i+1]; 
            end
            full_queue <= 0;
            counter <= counter - 1;
        end

        if(fin_flag)begin
            colour_queue[counter] <=  colour_i;
            xqueue[counter] <= xpixel_i;
            yqueue[counter] <= ypixel_i;
            counter <= counter + 1;
        end
    end
end

endmodule

top.sv
module top #(
    parameter   DATA_WIDTH = 32,
                RBG_SIZE = 24
)(
    input logic                     clk,
    input logic                     reset,
    input logic                     fin_flag,
    input logic [RBG_SIZE-1:0]      colour_i,
    input logic [DATA_WIDTH-1:0]    xpixel_i,
    input logic [DATA_WIDTH-1:0]    ypixel_i,
    input logic                     ready,

    output logic                    full_queue,
    output logic [RBG_SIZE-1:0]     colour_o,

    // flags for pixel generator
    output logic                    first,
    output logic                    last_x,
    output logic                    last_y,
    output logic                    valid

);

logic [DATA_WIDTH-1:0]  xpixel_wire;
logic [DATA_WIDTH-1:0]  ypixel_wire;
logic [RBG_SIZE-1:0]    colour_wire;
logic                   en_wire;


queue queue_block(
   .clk(clk),
   .reset(reset),
   .fin_flag(fin_flag),
   .colour_i(colour_i),
   .xpixel_i(xpixel_i),
   .ypixel_i(ypixel_i),
   .xpixel_check(xpixel_wire),
   .ypixel_check(ypixel_wire),
   .colour_o(colour_wire),
   .full_queue(full_queue),
   .en(en_wire) 
);

combinator combinator_block(
    .clk(clk),
    .reset(reset),
    .colour_i(colour_wire),
    .en(en_wire),
    .ready(ready),
    .next_xpixel(xpixel_wire),
    .next_ypixel(ypixel_wire),
    .colour_o(colour_o),
    .first(first),
    .last_x(last_x),
    .last_y(last_y),
    .valid(valid)
);

endmodule

top.vcd
$version Generated by VerilatedVcd $end
$date Wed Jun  5 13:55:37 2024 $end
$timescale 1ps $end

 $scope module TOP $end
  $var wire  1 ; clk $end
  $var wire 24 > colour_i [23:0] $end
  $var wire 24 C colour_o [23:0] $end
  $var wire  1 = fin_flag $end
  $var wire  1 D first $end
  $var wire  1 B full_queue $end
  $var wire  1 E last_x $end
  $var wire  1 F last_y $end
  $var wire  1 A ready $end
  $var wire  1 < reset $end
  $var wire  1 G valid $end
  $var wire 32 ? xpixel_i [31:0] $end
  $var wire 32 @ ypixel_i [31:0] $end
  $scope module top $end
   $var wire 32 H DATA_WIDTH [31:0] $end
   $var wire 32 I RBG_SIZE [31:0] $end
   $var wire  1 ; clk $end
   $var wire 24 > colour_i [23:0] $end
   $var wire 24 C colour_o [23:0] $end
   $var wire 24 % colour_wire [23:0] $end
   $var wire  1 & en_wire $end
   $var wire  1 = fin_flag $end
   $var wire  1 D first $end
   $var wire  1 B full_queue $end
   $var wire  1 E last_x $end
   $var wire  1 F last_y $end
   $var wire  1 A ready $end
   $var wire  1 < reset $end
   $var wire  1 G valid $end
   $var wire 32 ? xpixel_i [31:0] $end
   $var wire 32 # xpixel_wire [31:0] $end
   $var wire 32 @ ypixel_i [31:0] $end
   $var wire 32 $ ypixel_wire [31:0] $end
   $scope module combinator_block $end
    $var wire 32 H DATA_WIDTH [31:0] $end
    $var wire 32 I RBG_SIZE [31:0] $end
    $var wire 32 K SCREEN_HEIGHT [31:0] $end
    $var wire 32 J SCREEN_WIDTH [31:0] $end
    $var wire  1 ; clk $end
    $var wire 24 % colour_i [23:0] $end
    $var wire 24 C colour_o [23:0] $end
    $var wire  1 & en $end
    $var wire  1 D first $end
    $var wire  1 E last_x $end
    $var wire  1 F last_y $end
    $var wire 32 # next_xpixel [31:0] $end
    $var wire 32 $ next_ypixel [31:0] $end
    $var wire  1 A ready $end
    $var wire  1 < reset $end
    $var wire  1 G valid $end
    $var wire 32 ' xcount [31:0] $end
    $var wire 32 ( ycount [31:0] $end
   $upscope $end
   $scope module queue_block $end
    $var wire 32 M COUNTER_SIZE [31:0] $end
    $var wire 32 H DATA_WIDTH [31:0] $end
    $var wire 32 L QUEUE_SIZE [31:0] $end
    $var wire 32 I RBG_SIZE [31:0] $end
    $var wire  1 ; clk $end
    $var wire 24 > colour_i [23:0] $end
    $var wire 24 % colour_o [23:0] $end
    $var wire 24 ) colour_queue[0] [23:0] $end
    $var wire 24 * colour_queue[1] [23:0] $end
    $var wire 24 + colour_queue[2] [23:0] $end
    $var wire 24 , colour_queue[3] [23:0] $end
    $var wire 24 - colour_queue[4] [23:0] $end
    $var wire  3 8 counter [2:0] $end
    $var wire  1 & en $end
    $var wire  1 = fin_flag $end
    $var wire  1 B full_queue $end
    $var wire  1 < reset $end
    $var wire 32 # xpixel_check [31:0] $end
    $var wire 32 ? xpixel_i [31:0] $end
    $var wire 32 . xqueue[0] [31:0] $end
    $var wire 32 / xqueue[1] [31:0] $end
    $var wire 32 0 xqueue[2] [31:0] $end
    $var wire 32 1 xqueue[3] [31:0] $end
    $var wire 32 2 xqueue[4] [31:0] $end
    $var wire 32 $ ypixel_check [31:0] $end
    $var wire 32 @ ypixel_i [31:0] $end
    $var wire 32 3 yqueue[0] [31:0] $end
    $var wire 32 4 yqueue[1] [31:0] $end
    $var wire 32 5 yqueue[2] [31:0] $end
    $var wire 32 6 yqueue[3] [31:0] $end
    $var wire 32 7 yqueue[4] [31:0] $end
    $scope module unnamedblk1 $end
     $var wire 32 9 i [31:0] $end
    $upscope $end
    $scope module unnamedblk2 $end
     $var wire 32 : i [31:0] $end
    $upscope $end
   $upscope $end
  $upscope $end
 $upscope $end
$enddefinitions $end


#0
b00000000000000000000000000000000 #
b00000000000000000000000000000000 $
b000000000000000000000000 %
0&
b00000000000000000000000000000000 '
b00000000000000000000000000000000 (
b000000000000000000000000 )
b000000000000000000000000 *
b000000000000000000000000 +
b000000000000000000000000 ,
b000000000000000000000000 -
b00000000000000000000000000000000 .
b00000000000000000000000000000000 /
b00000000000000000000000000000000 0
b00000000000000000000000000000000 1
b00000000000000000000000000000000 2
b00000000000000000000000000000000 3
b00000000000000000000000000000000 4
b00000000000000000000000000000000 5
b00000000000000000000000000000000 6
b00000000000000000000000000000000 7
b000 8
b00000000000000000000000000000000 9
b00000000000000000000000000000000 :
1;
1<
1=
b000000000000000000000000 >
b00000000000000000000000000000000 ?
b00000000000000000000000000000000 @
1A
0B
b000000000000000000000000 C
0D
0E
0F
0G
b00000000000000000000000000100000 H
b00000000000000000000000000011000 I
b00000000000000000000001010000000 J
b00000000000000000000000111100000 K
b00000000000000000000000000000101 L
b00000000000000000000000000000011 M
#1
1&
0;
#2
b00000000000000000000000000000001 '
b00000000000000000000000111100000 (
b00000000000000000000000000000101 9
1;
0<
b00000000000000000000000111100000 @
1G
#3
0;
#4
b00000000000000000000000000000001 #
b00000000000000000000000111100000 $
b00000000000000000000000000000010 '
b00000000000000000000000111100000 3
b001 8
b00000000000000000000000000000100 :
1;
b000000000000000000000001 >
b00000000000000000000000000000001 ?
#5
0;
#6
b00000000000000000000000000000010 #
b00000000000000000000000000000011 '
b000000000000000000000001 *
b00000000000000000000000000000001 /
b00000000000000000000000111100000 4
b010 8
1;
b000000000000000000000010 >
b00000000000000000000000000000010 ?
#7
0;
#8
b00000000000000000000000000000011 #
b00000000000000000000000000000100 '
b000000000000000000000010 +
b00000000000000000000000000000010 0
b00000000000000000000000111100000 5
b011 8
1;
b000000000000000000000011 >
b00000000000000000000000000000011 ?
#9
0;
#10
b00000000000000000000000000000100 #
b00000000000000000000000000000101 '
b000000000000000000000011 ,
b00000000000000000000000000000011 1
b00000000000000000000000111100000 6
b100 8
1;
b000000000000000000000100 >
b00000000000000000000000000000100 ?
#11
0;
#12
b00000000000000000000000000000101 #
b00000000000000000000000000000110 '
b000000000000000000000100 -
b00000000000000000000000000000100 2
b00000000000000000000000111100000 7
b101 8
1;
b000000000000000000000101 >
b00000000000000000000000000000101 ?
1B
#13
0;
#14
b00000000000000000000000000000110 #
b00000000000000000000000000000111 '
b110 8
1;
b000000000000000000000110 >
b00000000000000000000000000000110 ?
0B
#15
0;
#16
b00000000000000000000000000000111 #
b00000000000000000000000000001000 '
b111 8
1;
b000000000000000000000111 >
b00000000000000000000000000000111 ?
#17
0;
#18
b00000000000000000000000000001000 #
b00000000000000000000000000001001 '
b000 8
1;
b000000000000000000001000 >
b00000000000000000000000000001000 ?
#19
0;
#20
b00000000000000000000000000001001 #
b00000000000000000000000000001010 '
b000000000000000000001000 )
b00000000000000000000000000001000 .
b001 8
1;
b000000000000000000001001 >
b00000000000000000000000000001001 ?
#21
0;
#22
b00000000000000000000000000001010 #
b00000000000000000000000000001011 '
b000000000000000000001001 *
b00000000000000000000000000001001 /
b010 8
1;
b000000000000000000001010 >
b00000000000000000000000000001010 ?
#23
0;
#24
b00000000000000000000000000001011 #
b00000000000000000000000000001100 '
b000000000000000000001010 +
b00000000000000000000000000001010 0
b011 8
1;
b000000000000000000001011 >
b00000000000000000000000000001011 ?
#25
0;
#26
b00000000000000000000000000001100 #
b00000000000000000000000000001101 '
b000000000000000000001011 ,
b00000000000000000000000000001011 1
b100 8
1;
b000000000000000000001100 >
b00000000000000000000000000001100 ?
#27
0;
#28
b00000000000000000000000000001101 #
b00000000000000000000000000001110 '
b000000000000000000001100 -
b00000000000000000000000000001100 2
b101 8
1;
b000000000000000000001101 >
b00000000000000000000000000001101 ?
1B
#29
0;
#30
b00000000000000000000000000001110 #
b00000000000000000000000000001111 '
b110 8
1;
b000000000000000000001110 >
b00000000000000000000000000001110 ?
0B
#31
0;
#32
b00000000000000000000000000001111 #
b00000000000000000000000000010000 '
b111 8
1;
b000000000000000000001111 >
b00000000000000000000000000001111 ?
#33
0;
#34
b00000000000000000000000000010000 #
b00000000000000000000000000010001 '
b000 8
1;
b000000000000000000010000 >
b00000000000000000000000000010000 ?
#35
0;
#36
b00000000000000000000000000010001 #
b00000000000000000000000000010010 '
b000000000000000000010000 )
b00000000000000000000000000010000 .
b001 8
1;
b000000000000000000010001 >
b00000000000000000000000000010001 ?
#37
0;
#38
b00000000000000000000000000010010 #
b00000000000000000000000000010011 '
b000000000000000000010001 *
b00000000000000000000000000010001 /
b010 8
1;
b000000000000000000010010 >
b00000000000000000000000000010010 ?
#39
0;
#40
b00000000000000000000000000010011 #
b00000000000000000000000000010100 '
b000000000000000000010010 +
b00000000000000000000000000010010 0
b011 8
1;
b000000000000000000010011 >
b00000000000000000000000000010011 ?
#41
0;
#42
b00000000000000000000000000010100 #
b00000000000000000000000000010101 '
b000000000000000000010011 ,
b00000000000000000000000000010011 1
b100 8
1;
b000000000000000000010100 >
b00000000000000000000000000010100 ?
#43
0;
#44
b00000000000000000000000000010101 #
b00000000000000000000000000010110 '
b000000000000000000010100 -
b00000000000000000000000000010100 2
b101 8
1;
b000000000000000000010101 >
b00000000000000000000000000010101 ?
1B
#45
0;
#46
b00000000000000000000000000010110 #
b00000000000000000000000000010111 '
b110 8
1;
b000000000000000000010110 >
b00000000000000000000000000010110 ?
0B
#47
0;
#48
b00000000000000000000000000010111 #
b00000000000000000000000000011000 '
b111 8
1;
b000000000000000000010111 >
b00000000000000000000000000010111 ?
#49
0;
#50
b00000000000000000000000000011000 #
b00000000000000000000000000011001 '
b000 8
1;
b000000000000000000011000 >
b00000000000000000000000000011000 ?
#51
0;
#52
b00000000000000000000000000011001 #
b00000000000000000000000000011010 '
b000000000000000000011000 )
b00000000000000000000000000011000 .
b001 8
1;
b000000000000000000011001 >
b00000000000000000000000000011001 ?
#53
0;
#54
b00000000000000000000000000011010 #
b00000000000000000000000000011011 '
b000000000000000000011001 *
b00000000000000000000000000011001 /
b010 8
1;
b000000000000000000011010 >
b00000000000000000000000000011010 ?
#55
0;
#56
b00000000000000000000000000011011 #
b00000000000000000000000000011100 '
b000000000000000000011010 +
b00000000000000000000000000011010 0
b011 8
1;
b000000000000000000011011 >
b00000000000000000000000000011011 ?
#57
0;
#58
b00000000000000000000000000011100 #
b00000000000000000000000000011101 '
b000000000000000000011011 ,
b00000000000000000000000000011011 1
b100 8
1;
b000000000000000000011100 >
b00000000000000000000000000011100 ?
#59
0;
#60
b00000000000000000000000000011101 #
b00000000000000000000000000011110 '
b000000000000000000011100 -
b00000000000000000000000000011100 2
b101 8
1;
b000000000000000000011101 >
b00000000000000000000000000011101 ?
1B
#61
0;
#62
b00000000000000000000000000011110 #
b00000000000000000000000000011111 '
b110 8
1;
b000000000000000000011110 >
b00000000000000000000000000011110 ?
0B
#63
0;
#64
b00000000000000000000000000011111 #
b00000000000000000000000000100000 '
b111 8
1;
b000000000000000000011111 >
b00000000000000000000000000011111 ?
#65
0;
#66
b00000000000000000000000000100000 #
b00000000000000000000000000100001 '
b000 8
1;
b000000000000000000100000 >
b00000000000000000000000000100000 ?
#67
0;
#68
b00000000000000000000000000100001 #
b00000000000000000000000000100010 '
b000000000000000000100000 )
b00000000000000000000000000100000 .
b001 8
1;
b000000000000000000100001 >
b00000000000000000000000000100001 ?
#69
0;
#70
b00000000000000000000000000100010 #
b00000000000000000000000000100011 '
b000000000000000000100001 *
b00000000000000000000000000100001 /
b010 8
1;
b000000000000000000100010 >
b00000000000000000000000000100010 ?
#71
0;
#72
b00000000000000000000000000100011 #
b00000000000000000000000000100100 '
b000000000000000000100010 +
b00000000000000000000000000100010 0
b011 8
1;
b000000000000000000100011 >
b00000000000000000000000000100011 ?
#73
0;
#74
b00000000000000000000000000100100 #
b00000000000000000000000000100101 '
b000000000000000000100011 ,
b00000000000000000000000000100011 1
b100 8
1;
b000000000000000000100100 >
b00000000000000000000000000100100 ?
#75
0;
#76
b00000000000000000000000000100101 #
b00000000000000000000000000100110 '
b000000000000000000100100 -
b00000000000000000000000000100100 2
b101 8
1;
b000000000000000000100101 >
b00000000000000000000000000100101 ?
1B
#77
0;
#78
b00000000000000000000000000100110 #
b00000000000000000000000000100111 '
b110 8
1;
b000000000000000000100110 >
b00000000000000000000000000100110 ?
0B
#79
0;
#80
b00000000000000000000000000100111 #
b00000000000000000000000000101000 '
b111 8
1;
b000000000000000000100111 >
b00000000000000000000000000100111 ?
#81
0;
#82
b00000000000000000000000000101000 #
b00000000000000000000000000101001 '
b000 8
1;
b000000000000000000101000 >
b00000000000000000000000000101000 ?
#83
0;
#84
b00000000000000000000000000101001 #
b00000000000000000000000000101010 '
b000000000000000000101000 )
b00000000000000000000000000101000 .
b001 8
1;
b000000000000000000101001 >
b00000000000000000000000000101001 ?
#85
0;
#86
b00000000000000000000000000101010 #
b00000000000000000000000000101011 '
b000000000000000000101001 *
b00000000000000000000000000101001 /
b010 8
1;
b000000000000000000101010 >
b00000000000000000000000000101010 ?
#87
0;
#88
b00000000000000000000000000101011 #
b00000000000000000000000000101100 '
b000000000000000000101010 +
b00000000000000000000000000101010 0
b011 8
1;
b000000000000000000101011 >
b00000000000000000000000000101011 ?
#89
0;
#90
b00000000000000000000000000101100 #
b00000000000000000000000000101101 '
b000000000000000000101011 ,
b00000000000000000000000000101011 1
b100 8
1;
b000000000000000000101100 >
b00000000000000000000000000101100 ?
#91
0;
#92
b00000000000000000000000000101101 #
b00000000000000000000000000101110 '
b000000000000000000101100 -
b00000000000000000000000000101100 2
b101 8
1;
b000000000000000000101101 >
b00000000000000000000000000101101 ?
1B
#93
0;
#94
b00000000000000000000000000101110 #
b00000000000000000000000000101111 '
b110 8
1;
b000000000000000000101110 >
b00000000000000000000000000101110 ?
0B
#95
0;
#96
b00000000000000000000000000101111 #
b00000000000000000000000000110000 '
b111 8
1;
b000000000000000000101111 >
b00000000000000000000000000101111 ?
#97
0;
#98
b00000000000000000000000000110000 #
b00000000000000000000000000110001 '
b000 8
1;
b000000000000000000110000 >
b00000000000000000000000000110000 ?
#99
0;
#100
b00000000000000000000000000110001 #
b00000000000000000000000000110010 '
b000000000000000000110000 )
b00000000000000000000000000110000 .
b001 8
1;
b000000000000000000110001 >
b00000000000000000000000000110001 ?
#101
0;
#102
b00000000000000000000000000110010 #
b00000000000000000000000000110011 '
b000000000000000000110001 *
b00000000000000000000000000110001 /
b010 8
1;
b000000000000000000110010 >
b00000000000000000000000000110010 ?
#103
0;
#104
b00000000000000000000000000110011 #
b00000000000000000000000000110100 '
b000000000000000000110010 +
b00000000000000000000000000110010 0
b011 8
1;
b000000000000000000110011 >
b00000000000000000000000000110011 ?
#105
0;
#106
b00000000000000000000000000110100 #
b00000000000000000000000000110101 '
b000000000000000000110011 ,
b00000000000000000000000000110011 1
b100 8
1;
b000000000000000000110100 >
b00000000000000000000000000110100 ?
#107
0;
#108
b00000000000000000000000000110101 #
b00000000000000000000000000110110 '
b000000000000000000110100 -
b00000000000000000000000000110100 2
b101 8
1;
b000000000000000000110101 >
b00000000000000000000000000110101 ?
1B
#109
0;
#110
b00000000000000000000000000110110 #
b00000000000000000000000000110111 '
b110 8
1;
b000000000000000000110110 >
b00000000000000000000000000110110 ?
0B
#111
0;
#112
b00000000000000000000000000110111 #
b00000000000000000000000000111000 '
b111 8
1;
b000000000000000000110111 >
b00000000000000000000000000110111 ?
#113
0;
#114
b00000000000000000000000000111000 #
b00000000000000000000000000111001 '
b000 8
1;
b000000000000000000111000 >
b00000000000000000000000000111000 ?
#115
0;
#116
b00000000000000000000000000111001 #
b00000000000000000000000000111010 '
b000000000000000000111000 )
b00000000000000000000000000111000 .
b001 8
1;
b000000000000000000111001 >
b00000000000000000000000000111001 ?
#117
0;
#118
b00000000000000000000000000111010 #
b00000000000000000000000000111011 '
b000000000000000000111001 *
b00000000000000000000000000111001 /
b010 8
1;
b000000000000000000111010 >
b00000000000000000000000000111010 ?
#119
0;
#120
b00000000000000000000000000111011 #
b00000000000000000000000000111100 '
b000000000000000000111010 +
b00000000000000000000000000111010 0
b011 8
1;
b000000000000000000111011 >
b00000000000000000000000000111011 ?
#121
0;
#122
b00000000000000000000000000111100 #
b00000000000000000000000000111101 '
b000000000000000000111011 ,
b00000000000000000000000000111011 1
b100 8
1;
b000000000000000000111100 >
b00000000000000000000000000111100 ?
#123
0;
#124
b00000000000000000000000000111101 #
b00000000000000000000000000111110 '
b000000000000000000111100 -
b00000000000000000000000000111100 2
b101 8
1;
b000000000000000000111101 >
b00000000000000000000000000111101 ?
1B
#125
0;
#126
b00000000000000000000000000111110 #
b00000000000000000000000000111111 '
b110 8
1;
b000000000000000000111110 >
b00000000000000000000000000111110 ?
0B
#127
0;
#128
b00000000000000000000000000111111 #
b00000000000000000000000001000000 '
b111 8
1;
b000000000000000000111111 >
b00000000000000000000000000111111 ?
#129
0;
#130
b00000000000000000000000001000000 #
b00000000000000000000000001000001 '
b000 8
1;
b000000000000000001000000 >
b00000000000000000000000001000000 ?
#131
0;
#132
b00000000000000000000000001000001 #
b00000000000000000000000001000010 '
b000000000000000001000000 )
b00000000000000000000000001000000 .
b001 8
1;
b000000000000000001000001 >
b00000000000000000000000001000001 ?
#133
0;
#134
b00000000000000000000000001000010 #
b00000000000000000000000001000011 '
b000000000000000001000001 *
b00000000000000000000000001000001 /
b010 8
1;
b000000000000000001000010 >
b00000000000000000000000001000010 ?
#135
0;
#136
b00000000000000000000000001000011 #
b00000000000000000000000001000100 '
b000000000000000001000010 +
b00000000000000000000000001000010 0
b011 8
1;
b000000000000000001000011 >
b00000000000000000000000001000011 ?
#137
0;
#138
b00000000000000000000000001000100 #
b00000000000000000000000001000101 '
b000000000000000001000011 ,
b00000000000000000000000001000011 1
b100 8
1;
b000000000000000001000100 >
b00000000000000000000000001000100 ?
#139
0;
#140
b00000000000000000000000001000101 #
b00000000000000000000000001000110 '
b000000000000000001000100 -
b00000000000000000000000001000100 2
b101 8
1;
b000000000000000001000101 >
b00000000000000000000000001000101 ?
1B
#141
0;
#142
b00000000000000000000000001000110 #
b00000000000000000000000001000111 '
b110 8
1;
b000000000000000001000110 >
b00000000000000000000000001000110 ?
0B
#143
0;
#144
b00000000000000000000000001000111 #
b00000000000000000000000001001000 '
b111 8
1;
b000000000000000001000111 >
b00000000000000000000000001000111 ?
#145
0;
#146
b00000000000000000000000001001000 #
b00000000000000000000000001001001 '
b000 8
1;
b000000000000000001001000 >
b00000000000000000000000001001000 ?
#147
0;
#148
b00000000000000000000000001001001 #
b00000000000000000000000001001010 '
b000000000000000001001000 )
b00000000000000000000000001001000 .
b001 8
1;
b000000000000000001001001 >
b00000000000000000000000001001001 ?
#149
0;
#150
b00000000000000000000000001001010 #
b00000000000000000000000001001011 '
b000000000000000001001001 *
b00000000000000000000000001001001 /
b010 8
1;
b000000000000000001001010 >
b00000000000000000000000001001010 ?
#151
0;
#152
b00000000000000000000000001001011 #
b00000000000000000000000001001100 '
b000000000000000001001010 +
b00000000000000000000000001001010 0
b011 8
1;
b000000000000000001001011 >
b00000000000000000000000001001011 ?
#153
0;
#154
b00000000000000000000000001001100 #
b00000000000000000000000001001101 '
b000000000000000001001011 ,
b00000000000000000000000001001011 1
b100 8
1;
b000000000000000001001100 >
b00000000000000000000000001001100 ?
#155
0;
#156
b00000000000000000000000001001101 #
b00000000000000000000000001001110 '
b000000000000000001001100 -
b00000000000000000000000001001100 2
b101 8
1;
b000000000000000001001101 >
b00000000000000000000000001001101 ?
1B
#157
0;
#158
b00000000000000000000000001001110 #
b00000000000000000000000001001111 '
b110 8
1;
b000000000000000001001110 >
b00000000000000000000000001001110 ?
0B
#159
0;
#160
b00000000000000000000000001001111 #
b00000000000000000000000001010000 '
b111 8
1;
b000000000000000001001111 >
b00000000000000000000000001001111 ?
#161
0;
#162
b00000000000000000000000001010000 #
b00000000000000000000000001010001 '
b000 8
1;
b000000000000000001010000 >
b00000000000000000000000001010000 ?
#163
0;
#164
b00000000000000000000000001010001 #
b00000000000000000000000001010010 '
b000000000000000001010000 )
b00000000000000000000000001010000 .
b001 8
1;
b000000000000000001010001 >
b00000000000000000000000001010001 ?
#165
0;
#166
b00000000000000000000000001010010 #
b00000000000000000000000001010011 '
b000000000000000001010001 *
b00000000000000000000000001010001 /
b010 8
1;
b000000000000000001010010 >
b00000000000000000000000001010010 ?
#167
0;
#168
b00000000000000000000000001010011 #
b00000000000000000000000001010100 '
b000000000000000001010010 +
b00000000000000000000000001010010 0
b011 8
1;
b000000000000000001010011 >
b00000000000000000000000001010011 ?
#169
0;
#170
b00000000000000000000000001010100 #
b00000000000000000000000001010101 '
b000000000000000001010011 ,
b00000000000000000000000001010011 1
b100 8
1;
b000000000000000001010100 >
b00000000000000000000000001010100 ?
#171
0;
#172
b00000000000000000000000001010101 #
b00000000000000000000000001010110 '
b000000000000000001010100 -
b00000000000000000000000001010100 2
b101 8
1;
b000000000000000001010101 >
b00000000000000000000000001010101 ?
1B
#173
0;
#174
b00000000000000000000000001010110 #
b00000000000000000000000001010111 '
b110 8
1;
b000000000000000001010110 >
b00000000000000000000000001010110 ?
0B
#175
0;
#176
b00000000000000000000000001010111 #
b00000000000000000000000001011000 '
b111 8
1;
b000000000000000001010111 >
b00000000000000000000000001010111 ?
#177
0;
#178
b00000000000000000000000001011000 #
b00000000000000000000000001011001 '
b000 8
1;
b000000000000000001011000 >
b00000000000000000000000001011000 ?
#179
0;
#180
b00000000000000000000000001011001 #
b00000000000000000000000001011010 '
b000000000000000001011000 )
b00000000000000000000000001011000 .
b001 8
1;
b000000000000000001011001 >
b00000000000000000000000001011001 ?
#181
0;
#182
b00000000000000000000000001011010 #
b00000000000000000000000001011011 '
b000000000000000001011001 *
b00000000000000000000000001011001 /
b010 8
1;
b000000000000000001011010 >
b00000000000000000000000001011010 ?
#183
0;
#184
b00000000000000000000000001011011 #
b00000000000000000000000001011100 '
b000000000000000001011010 +
b00000000000000000000000001011010 0
b011 8
1;
b000000000000000001011011 >
b00000000000000000000000001011011 ?
#185
0;
#186
b00000000000000000000000001011100 #
b00000000000000000000000001011101 '
b000000000000000001011011 ,
b00000000000000000000000001011011 1
b100 8
1;
b000000000000000001011100 >
b00000000000000000000000001011100 ?
#187
0;
#188
b00000000000000000000000001011101 #
b00000000000000000000000001011110 '
b000000000000000001011100 -
b00000000000000000000000001011100 2
b101 8
1;
b000000000000000001011101 >
b00000000000000000000000001011101 ?
1B
#189
0;
#190
b00000000000000000000000001011110 #
b00000000000000000000000001011111 '
b110 8
1;
b000000000000000001011110 >
b00000000000000000000000001011110 ?
0B
#191
0;
#192
b00000000000000000000000001011111 #
b00000000000000000000000001100000 '
b111 8
1;
b000000000000000001011111 >
b00000000000000000000000001011111 ?
#193
0;
#194
b00000000000000000000000001100000 #
b00000000000000000000000001100001 '
b000 8
1;
b000000000000000001100000 >
b00000000000000000000000001100000 ?
#195
0;
#196
b00000000000000000000000001100001 #
b00000000000000000000000001100010 '
b000000000000000001100000 )
b00000000000000000000000001100000 .
b001 8
1;
b000000000000000001100001 >
b00000000000000000000000001100001 ?
#197
0;
#198
b00000000000000000000000001100010 #
b00000000000000000000000001100011 '
b000000000000000001100001 *
b00000000000000000000000001100001 /
b010 8
1;
b000000000000000001100010 >
b00000000000000000000000001100010 ?
#199
0;
#200
b00000000000000000000000001100011 #
b00000000000000000000000001100100 '
b000000000000000001100010 +
b00000000000000000000000001100010 0
b011 8
1;
b000000000000000001100011 >
b00000000000000000000000001100011 ?
#201
0;
#202
b00000000000000000000000001100100 #
b00000000000000000000000001100101 '
b000000000000000001100011 ,
b00000000000000000000000001100011 1
b100 8
1;
b000000000000000001100100 >
b00000000000000000000000001100100 ?
#203
0;
#204
b00000000000000000000000001100101 #
b00000000000000000000000001100110 '
b000000000000000001100100 -
b00000000000000000000000001100100 2
b101 8
1;
b000000000000000001100101 >
b00000000000000000000000001100101 ?
1B
#205
0;
#206
b00000000000000000000000001100110 #
b00000000000000000000000001100111 '
b110 8
1;
b000000000000000001100110 >
b00000000000000000000000001100110 ?
0B
#207
0;
#208
b00000000000000000000000001100111 #
b00000000000000000000000001101000 '
b111 8
1;
b000000000000000001100111 >
b00000000000000000000000001100111 ?
#209
0;
#210
b00000000000000000000000001101000 #
b00000000000000000000000001101001 '
b000 8
1;
b000000000000000001101000 >
b00000000000000000000000001101000 ?
#211
0;
#212
b00000000000000000000000001101001 #
b00000000000000000000000001101010 '
b000000000000000001101000 )
b00000000000000000000000001101000 .
b001 8
1;
b000000000000000001101001 >
b00000000000000000000000001101001 ?
#213
0;
#214
b00000000000000000000000001101010 #
b00000000000000000000000001101011 '
b000000000000000001101001 *
b00000000000000000000000001101001 /
b010 8
1;
b000000000000000001101010 >
b00000000000000000000000001101010 ?
#215
0;
#216
b00000000000000000000000001101011 #
b00000000000000000000000001101100 '
b000000000000000001101010 +
b00000000000000000000000001101010 0
b011 8
1;
b000000000000000001101011 >
b00000000000000000000000001101011 ?
#217
0;
#218
b00000000000000000000000001101100 #
b00000000000000000000000001101101 '
b000000000000000001101011 ,
b00000000000000000000000001101011 1
b100 8
1;
b000000000000000001101100 >
b00000000000000000000000001101100 ?
#219
0;
#220
b00000000000000000000000001101101 #
b00000000000000000000000001101110 '
b000000000000000001101100 -
b00000000000000000000000001101100 2
b101 8
1;
b000000000000000001101101 >
b00000000000000000000000001101101 ?
1B
#221
0;
